gitlabdata/__init__.py
gitlabdata/orchestration_utils.py
tests/__init__.py
tests/test_orchestration_utils.py
gitlabdata-0.3.40.dist-info/LICENSE
gitlabdata-0.3.40.dist-info/METADATA
gitlabdata-0.3.40.dist-info/WHEEL
gitlabdata-0.3.40.dist-info/top_level.txt
gitlabdata-0.3.40.dist-info/RECORD
