Metadata-Version: 2.1
Name: gitlabdata
Version: 0.3.40
Summary: GitLab Data Utils
Home-page: https://gitlab.com/gitlab-data/gitlab-data-utils
Author: GitLab Data Team
Author-email: data@gitlab.com
License: UNKNOWN
Platform: UNKNOWN
Requires-Dist: snowflake-sqlalchemy (<2.0,>=1.1.10)
Requires-Dist: snowflake-connector-python[pandas] (>=2.7.8)
Requires-Dist: pandas (>=0.25.3)
Requires-Dist: pyyaml (<=6.0.2,>=6.0.0)
Requires-Dist: pygsheets (>=2.0.5)
